analyze_site
