Metadata-Version: 1.1
Name: analyze-site
Version: 0.1.3
Summary: Utility to crawl web site looking for key words
Home-page: https://github.com/OV105/site-analyzer
Author: Tim Lee
Author-email: timhl81@gmail.com
License: Apache 2.0
Keywords: web,crawl,analyze
Platform: UNKNOWN
Classifier: Topic :: Utilities
Classifier: License :: OSI Approved :: Apache Software License
Classifier: Development Status :: 4 - Beta
